zookeeper_watcher
