Metadata-Version: 1.1
Name: Zookeeper-Watcher
Version: 0.1.3
Summary: Watches a designated node in Zookeeper for data or member changes and trigger a function when an event is detected.
Home-page: https://github.com/Bogdan-Alexandrescu/Zookeeper-Watcher
Author: @balex
Author-email: balex@ucdavis.edu
License: MIT
Keywords: zookeeper watch watcher kazoo nodes children
Platform: any
Classifier: Development Status :: 3 - Alpha
Classifier: Environment :: Web Environment
Classifier: Intended Audience :: Developers
Classifier: Topic :: Software Development :: Build Tools
Classifier: License :: OSI Approved :: MIT License
Classifier: Operating System :: POSIX
Classifier: Programming Language :: Python :: 2.7
